{
    "id": "ppr010",
    "title": "Általános ismeretek",
    "image_title": "elte_sek_pti",
    "image_url": "",
    "description": "Általánosabb, több helyről kiemelt kérdések",
    "time_seconds": 300,
    "questions": [
      {
        "id": "ppr010q001",
        "question": "Milyen szakirányok érhetőek el az ELTE programtervező informatikus képzésén?",
        "answers": [
          {
            "identifier": "A",
            "answer": "Csak az alapszak érhető el."
          },
          {
            "identifier": "B",
            "answer": "Az alapszak és a szoftvermérnöki szakirány is elérhető."
          },
          {
            "identifier": "C",
            "answer": "Csak a szoftvermérnöki szakirány érhető el."
          }
        ],
        "correct_answer": "B"
      },
      {
        "id": "ppr010q002",
        "question": "Hol érhető el az ELTE programtervező informatikus képzése?",
        "answers": [
          {
            "identifier": "A",
            "answer": "Csak a budapesti ELTE-n."
          },
          {
            "identifier": "B",
            "answer": "Csak a szombathelyi ELTE-n"
          },
          {
            "identifier": "C",
            "answer": "Mindkettőn"
          },
          {
            "identifier": "D",
            "answer": "Egyiken sem"
          }
        ],
        "correct_answer": "C"
      },
      {
        "id": "ppr010q003",
        "question": "Milyen ismereteket sajátíthatnak el azok, akik az ELTE programtervező informatikus képzésén vesznek részt?",
        "answers": [
          {
            "identifier": "A",
            "answer": "Csak elméleti ismereteket."
          },
          {
            "identifier": "B",
            "answer": "Speciális fejlesztői-alkalmazói ismereteket."
          },
          {
            "identifier": "C",
            "answer": "Csak web- és cloud programozási ismereteket."
          },
          {
            "identifier": "D",
            "answer": "Mind elméleti, mind speciális gyakorlati ismereteket."
          }
        ],
        "correct_answer": "D"
      },
      {
        "id": "ppr010q004",
        "question": "Milyen jellegű projekteken dolgozhatnak az ELTE programtervező informatikus képzésén résztvevő hallgatók?",
        "answers": [
          {
            "identifier": "A",
            "answer": "Csak magyar nyelvű projekteken."
          },
          {
            "identifier": "B",
            "answer": "Mind magyar, mind nemzetközi projekteken."
          },
          {
            "identifier": "C",
            "answer": "Csak nemzetközi projekteken."
          }
        ],
        "correct_answer": "B"
      },
      {
        "id": "ppr010q005",
        "question": "Milyen szakképzettség szerepel az oklevélben?",
        "answers": [
          {
            "identifier": "A",
            "answer": "Programtervező Informatikus"
          },
          {
            "identifier": "B",
            "answer": "Szoftvermérnök"
          }
        ],
        "correct_answer": "A"
      }
    ]
  }